{
	"configurations" : 
	[
		{
			"directories" : 
			[
				{
					"build" : ".",
					"childIndexes" : 
					[
						1,
						2,
						4,
						5
					],
					"hasInstallRule" : true,
					"minimumCMakeVersion" : 
					{
						"string" : "2.8"
					},
					"projectIndex" : 0,
					"source" : "."
				},
				{
					"build" : "external",
					"minimumCMakeVersion" : 
					{
						"string" : "2.8"
					},
					"parentIndex" : 0,
					"projectIndex" : 1,
					"source" : "external",
					"targetIndexes" : 
					[
						3
					]
				},
				{
					"build" : "external/glfw",
					"childIndexes" : 
					[
						3
					],
					"hasInstallRule" : true,
					"minimumCMakeVersion" : 
					{
						"string" : "3.1"
					},
					"parentIndex" : 0,
					"projectIndex" : 2,
					"source" : "external/glfw",
					"targetIndexes" : 
					[
						4
					]
				},
				{
					"build" : "external/glfw/src",
					"hasInstallRule" : true,
					"minimumCMakeVersion" : 
					{
						"string" : "3.1"
					},
					"parentIndex" : 2,
					"projectIndex" : 2,
					"source" : "external/glfw/src",
					"targetIndexes" : 
					[
						2
					]
				},
				{
					"build" : "LunarEngine",
					"minimumCMakeVersion" : 
					{
						"string" : "2.8"
					},
					"parentIndex" : 0,
					"projectIndex" : 3,
					"source" : "LunarEngine",
					"targetIndexes" : 
					[
						0
					]
				},
				{
					"build" : "sandbox",
					"minimumCMakeVersion" : 
					{
						"string" : "2.8"
					},
					"parentIndex" : 0,
					"projectIndex" : 4,
					"source" : "sandbox",
					"targetIndexes" : 
					[
						1
					]
				}
			],
			"name" : "Debug",
			"projects" : 
			[
				{
					"childIndexes" : 
					[
						1,
						2,
						3,
						4
					],
					"directoryIndexes" : 
					[
						0
					],
					"name" : "Lunar"
				},
				{
					"directoryIndexes" : 
					[
						1
					],
					"name" : "external",
					"parentIndex" : 0,
					"targetIndexes" : 
					[
						3
					]
				},
				{
					"directoryIndexes" : 
					[
						2,
						3
					],
					"name" : "GLFW",
					"parentIndex" : 0,
					"targetIndexes" : 
					[
						2,
						4
					]
				},
				{
					"directoryIndexes" : 
					[
						4
					],
					"name" : "LunarEngine",
					"parentIndex" : 0,
					"targetIndexes" : 
					[
						0
					]
				},
				{
					"directoryIndexes" : 
					[
						5
					],
					"name" : "Sandbox",
					"parentIndex" : 0,
					"targetIndexes" : 
					[
						1
					]
				}
			],
			"targets" : 
			[
				{
					"directoryIndex" : 4,
					"id" : "LunarEngine::@42630e7590b9e7683b8d",
					"jsonFile" : "target-LunarEngine-Debug-ceff38bef0a64e68b2c2.json",
					"name" : "LunarEngine",
					"projectIndex" : 3
				},
				{
					"directoryIndex" : 5,
					"id" : "Sandbox::@e49c0a52b1bf699b6c68",
					"jsonFile" : "target-Sandbox-Debug-cf666db1d7b2e15a3fcb.json",
					"name" : "Sandbox",
					"projectIndex" : 4
				},
				{
					"directoryIndex" : 3,
					"id" : "glfw::@ca12bac854c2ac6b2230",
					"jsonFile" : "target-glfw-Debug-1d03fded24bdb3346658.json",
					"name" : "glfw",
					"projectIndex" : 2
				},
				{
					"directoryIndex" : 1,
					"id" : "ktx::@89556154f30252d09d22",
					"jsonFile" : "target-ktx-Debug-188417458a30c8ebb329.json",
					"name" : "ktx",
					"projectIndex" : 1
				},
				{
					"directoryIndex" : 2,
					"id" : "uninstall::@691b517da5fa0f694cd4",
					"jsonFile" : "target-uninstall-Debug-d52ce8b31e4d39fb74d3.json",
					"name" : "uninstall",
					"projectIndex" : 2
				}
			]
		}
	],
	"kind" : "codemodel",
	"paths" : 
	{
		"build" : "D:/code/LunarEngine/out/build/x64-Debug",
		"source" : "D:/code/LunarEngine"
	},
	"version" : 
	{
		"major" : 2,
		"minor" : 0
	}
}
